piplates/A2D.py
piplates/ANFUNC.py
piplates/BASE.py
piplates/BUTTON.py
piplates/DAQC2help.txt
piplates/DAQC2plate.py
piplates/DAQChelp.txt
piplates/DAQCplate.py
piplates/DIO.py
piplates/LED.py
piplates/METER.py
piplates/MOTORhelp.txt
piplates/MOTORplate.py
piplates/POWERhelp.txt
piplates/POWERplate.py
piplates/PWM.py
piplates/RANGE.py
piplates/RELAY.py
piplates/RELAY2help.txt
piplates/RELAYhelp.txt
piplates/RELAYplate.py
piplates/RELAYplate2.py
piplates/SERVO.py
piplates/TEMP.py
piplates/THERMOhelp.txt
piplates/THERMOplate.py
piplates/TINKERhelp.txt
piplates/TINKERplate.py
piplates/__init__.py
pi_plates-8.0.dist-info/METADATA
pi_plates-8.0.dist-info/WHEEL
pi_plates-8.0.dist-info/desktop.ini
pi_plates-8.0.dist-info/top_level.txt
pi_plates-8.0.dist-info/RECORD
