Metadata-Version: 2.1
Name: pi-plates
Version: 8.0
Summary: Pi-Plates library setup
Home-page: https://www.pi-plates.com
Author: Jerry Wasinger, WallyWare, inc.
Author-email: support@pi-plates.com
License: BSD
Keywords: pi-plates,data acquisition,raspberry pi,relays,motors,temperature sensing,HATs
Platform: UNKNOWN
